lightgbmlss/__init__.py
lightgbmlss/logger.py
lightgbmlss/model.py
lightgbmlss/utils.py
lightgbmlss/datasets/__init__.py
lightgbmlss/datasets/data_loader.py
lightgbmlss/datasets/gaussian_test_sim.csv
lightgbmlss/datasets/gaussian_train_sim.csv
lightgbmlss/datasets/studentT_test_sim.csv
lightgbmlss/datasets/studentT_train_sim.csv
lightgbmlss/distributions/Beta.py
lightgbmlss/distributions/Cauchy.py
lightgbmlss/distributions/Expectile.py
lightgbmlss/distributions/Gamma.py
lightgbmlss/distributions/Gaussian.py
lightgbmlss/distributions/Gumbel.py
lightgbmlss/distributions/Laplace.py
lightgbmlss/distributions/LogNormal.py
lightgbmlss/distributions/Mixture.py
lightgbmlss/distributions/NegativeBinomial.py
lightgbmlss/distributions/Poisson.py
lightgbmlss/distributions/SplineFlow.py
lightgbmlss/distributions/StudentT.py
lightgbmlss/distributions/Weibull.py
lightgbmlss/distributions/ZABeta.py
lightgbmlss/distributions/ZAGamma.py
lightgbmlss/distributions/ZALN.py
lightgbmlss/distributions/ZINB.py
lightgbmlss/distributions/ZIPoisson.py
lightgbmlss/distributions/__init__.py
lightgbmlss/distributions/distribution_utils.py
lightgbmlss/distributions/flow_utils.py
lightgbmlss/distributions/mixture_distribution_utils.py
lightgbmlss/distributions/zero_inflated.py
lightgbmlss-0.4.2.dist-info/LICENSE.txt
lightgbmlss-0.4.2.dist-info/METADATA
lightgbmlss-0.4.2.dist-info/WHEEL
lightgbmlss-0.4.2.dist-info/top_level.txt
lightgbmlss-0.4.2.dist-info/RECORD
