Metadata-Version: 2.1
Name: lightgbmlss
Version: 0.4.2
Summary: LightGBMLSS - An extension of LightGBM to probabilistic modelling.
Author-email: Alexander März <alex.maerz@gmx.net>
Maintainer-email: Alexander März <alex.maerz@gmx.net>
License: 
Project-URL: Homepage, https://github.com/StatMixedML/LightGBMLSS
Project-URL: Documentation, https://statmixedml.github.io/LightGBMLSS/
Keywords: distributional regression,mixture density model,normalizing flow,prediction intervals,probabilistic modelling,uncertainty estimation
Classifier: Programming Language :: Python :: 3.10
Classifier: Programming Language :: Python :: 3.11
Classifier: Operating System :: OS Independent
Requires-Python: >=3.10
License-File: LICENSE.txt
Requires-Dist: lightgbm ~=4.2.0
Requires-Dist: torch ~=2.1.2
Requires-Dist: pyro-ppl ~=1.8.6
Requires-Dist: optuna ~=3.5.0
Requires-Dist: properscoring ~=0.1
Requires-Dist: scikit-learn ~=1.4.0
Requires-Dist: numpy ~=1.26.3
Requires-Dist: pandas ~=2.1.4
Requires-Dist: plotnine ~=0.12.4
Requires-Dist: scipy ~=1.11.4
Requires-Dist: shap ~=0.44.0
Requires-Dist: seaborn ~=0.13.1
Requires-Dist: tqdm ~=4.66.1
Requires-Dist: matplotlib ~=3.8.2
Requires-Dist: ipython ~=8.20.0
